<options>
  <configurable id="preferences.keymap" configurable_name="키맵">
    <option name="" path="ActionManager" hit="" />
    <option name="gsp" path="ActionManager" hit="GSP" />
    <option name="grails" path="ActionManager" hit="Grails" />
    <option name="editor" path="ActionManager" hit="Grails Editor Toolbar" />
    <option name="grails" path="ActionManager" hit="Grails Editor Toolbar" />
    <option name="toolbar" path="ActionManager" hit="Grails Editor Toolbar" />
    <option name="grails" path="ActionManager" hit="Grails SDK 구성" />
    <option name="sdk" path="ActionManager" hit="Grails SDK 구성" />
    <option name="구성" path="ActionManager" hit="Grails SDK 구성" />
    <option name="grails" path="ActionManager" hit="Grails 명령어 실행" />
    <option name="명령어" path="ActionManager" hit="Grails 명령어 실행" />
    <option name="실행" path="ActionManager" hit="Grails 명령어 실행" />
    <option name="grails" path="ActionManager" hit="Grails 빌드 설정에 맞도록 IntelliJ IDEA 프로젝트 구조를 새로고침합니다." />
    <option name="idea" path="ActionManager" hit="Grails 빌드 설정에 맞도록 IntelliJ IDEA 프로젝트 구조를 새로고침합니다." />
    <option name="intellij" path="ActionManager" hit="Grails 빌드 설정에 맞도록 IntelliJ IDEA 프로젝트 구조를 새로고침합니다." />
    <option name="구조를" path="ActionManager" hit="Grails 빌드 설정에 맞도록 IntelliJ IDEA 프로젝트 구조를 새로고침합니다." />
    <option name="맞도록" path="ActionManager" hit="Grails 빌드 설정에 맞도록 IntelliJ IDEA 프로젝트 구조를 새로고침합니다." />
    <option name="빌드" path="ActionManager" hit="Grails 빌드 설정에 맞도록 IntelliJ IDEA 프로젝트 구조를 새로고침합니다." />
    <option name="새로고침합니다" path="ActionManager" hit="Grails 빌드 설정에 맞도록 IntelliJ IDEA 프로젝트 구조를 새로고침합니다." />
    <option name="설정에" path="ActionManager" hit="Grails 빌드 설정에 맞도록 IntelliJ IDEA 프로젝트 구조를 새로고침합니다." />
    <option name="프로젝트" path="ActionManager" hit="Grails 빌드 설정에 맞도록 IntelliJ IDEA 프로젝트 구조를 새로고침합니다." />
    <option name="grails" path="ActionManager" hit="Ajustes de sincronización de Grails" />
    <option name="동기화" path="ActionManager" hit="Ajustes de sincronización de Grails" />
    <option name="설정" path="ActionManager" hit="Ajustes de sincronización de Grails" />
    <option name="grails" path="ActionManager" hit="Grails 웹 아카이브 만들기" />
    <option name="만들기" path="ActionManager" hit="Grails 웹 아카이브 만들기" />
    <option name="아카이브" path="ActionManager" hit="Grails 웹 아카이브 만들기" />
    <option name="웹" path="ActionManager" hit="Grails 웹 아카이브 만들기" />
    <option name="ui에서" path="ActionManager" hit="UI에서 플러그인 관리" />
    <option name="관리" path="ActionManager" hit="UI에서 플러그인 관리" />
    <option name="플러그인" path="ActionManager" hit="UI에서 플러그인 관리" />
    <option name="도메인" path="ActionManager" hit="도메인 생성" />
    <option name="생성" path="ActionManager" hit="도메인 생성" />
    <option name="도메인으로" path="ActionManager" hit="도메인으로 이동" />
    <option name="이동" path="ActionManager" hit="도메인으로 이동" />
    <option name="뷰" path="ActionManager" hit="뷰" />
    <option name="뷰로" path="ActionManager" hit="뷰로 이동" />
    <option name="이동" path="ActionManager" hit="뷰로 이동" />
    <option name="grails" path="ActionManager" hit="새 Grails 도메인 클래스 생성" />
    <option name="도메인" path="ActionManager" hit="새 Grails 도메인 클래스 생성" />
    <option name="새" path="ActionManager" hit="새 Grails 도메인 클래스 생성" />
    <option name="생성" path="ActionManager" hit="새 Grails 도메인 클래스 생성" />
    <option name="클래스" path="ActionManager" hit="새 Grails 도메인 클래스 생성" />
    <option name="grails" path="ActionManager" hit="새 Grails 서비스 클래스 생성" />
    <option name="새" path="ActionManager" hit="새 Grails 서비스 클래스 생성" />
    <option name="생성" path="ActionManager" hit="새 Grails 서비스 클래스 생성" />
    <option name="서비스" path="ActionManager" hit="새 Grails 서비스 클래스 생성" />
    <option name="클래스" path="ActionManager" hit="새 Grails 서비스 클래스 생성" />
    <option name="grails" path="ActionManager" hit="새 Grails 스크립트 생성" />
    <option name="새" path="ActionManager" hit="새 Grails 스크립트 생성" />
    <option name="생성" path="ActionManager" hit="새 Grails 스크립트 생성" />
    <option name="스크립트" path="ActionManager" hit="새 Grails 스크립트 생성" />
    <option name="grails" path="ActionManager" hit="새 Grails 인터셉터 클래스 생성" />
    <option name="새" path="ActionManager" hit="새 Grails 인터셉터 클래스 생성" />
    <option name="생성" path="ActionManager" hit="새 Grails 인터셉터 클래스 생성" />
    <option name="인터셉터" path="ActionManager" hit="새 Grails 인터셉터 클래스 생성" />
    <option name="클래스" path="ActionManager" hit="새 Grails 인터셉터 클래스 생성" />
    <option name="grails" path="ActionManager" hit="새 Grails 컨트롤러 클래스 생성" />
    <option name="새" path="ActionManager" hit="새 Grails 컨트롤러 클래스 생성" />
    <option name="생성" path="ActionManager" hit="새 Grails 컨트롤러 클래스 생성" />
    <option name="컨트롤러" path="ActionManager" hit="새 Grails 컨트롤러 클래스 생성" />
    <option name="클래스" path="ActionManager" hit="새 Grails 컨트롤러 클래스 생성" />
    <option name="grails" path="ActionManager" hit="새 Grails 태그 라이브러리 생성" />
    <option name="라이브러리" path="ActionManager" hit="새 Grails 태그 라이브러리 생성" />
    <option name="새" path="ActionManager" hit="새 Grails 태그 라이브러리 생성" />
    <option name="생성" path="ActionManager" hit="새 Grails 태그 라이브러리 생성" />
    <option name="태그" path="ActionManager" hit="새 Grails 태그 라이브러리 생성" />
    <option name="grails" path="ActionManager" hit="새 Grails 필터 클래스 생성" />
    <option name="새" path="ActionManager" hit="새 Grails 필터 클래스 생성" />
    <option name="생성" path="ActionManager" hit="새 Grails 필터 클래스 생성" />
    <option name="클래스" path="ActionManager" hit="새 Grails 필터 클래스 생성" />
    <option name="필터" path="ActionManager" hit="새 Grails 필터 클래스 생성" />
    <option name="groovy" path="ActionManager" hit="새 Groovy 서버 페이지 생성" />
    <option name="새" path="ActionManager" hit="새 Groovy 서버 페이지 생성" />
    <option name="생성" path="ActionManager" hit="새 Groovy 서버 페이지 생성" />
    <option name="서버" path="ActionManager" hit="새 Groovy 서버 페이지 생성" />
    <option name="페이지" path="ActionManager" hit="새 Groovy 서버 페이지 생성" />
    <option name="만들기" path="ActionManager" hit="새로 만들기" />
    <option name="새로" path="ActionManager" hit="새로 만들기" />
    <option name="생성" path="ActionManager" hit="서비스 생성" />
    <option name="서비스" path="ActionManager" hit="서비스 생성" />
    <option name="서비스로" path="ActionManager" hit="서비스로 이동" />
    <option name="이동" path="ActionManager" hit="서비스로 이동" />
    <option name="생성" path="ActionManager" hit="스크립트 생성" />
    <option name="스크립트" path="ActionManager" hit="스크립트 생성" />
    <option name="생성" path="ActionManager" hit="웹 아카이브 생성" />
    <option name="아카이브" path="ActionManager" hit="웹 아카이브 생성" />
    <option name="웹" path="ActionManager" hit="웹 아카이브 생성" />
    <option name="생성" path="ActionManager" hit="인터셉터 생성" />
    <option name="인터셉터" path="ActionManager" hit="인터셉터 생성" />
    <option name="생성" path="ActionManager" hit="컨트롤러 생성" />
    <option name="컨트롤러" path="ActionManager" hit="컨트롤러 생성" />
    <option name="이동" path="ActionManager" hit="컨트롤러로 이동" />
    <option name="컨트롤러로" path="ActionManager" hit="컨트롤러로 이동" />
    <option name="라이브러리" path="ActionManager" hit="태그 라이브러리 생성" />
    <option name="생성" path="ActionManager" hit="태그 라이브러리 생성" />
    <option name="태그" path="ActionManager" hit="태그 라이브러리 생성" />
    <option name="이동" path="ActionManager" hit="테스트로 이동" />
    <option name="테스트로" path="ActionManager" hit="테스트로 이동" />
    <option name="플러그인" path="ActionManager" hit="플러그인" />
    <option name="생성" path="ActionManager" hit="필터 생성" />
    <option name="필터" path="ActionManager" hit="필터 생성" />
  </configurable>
</options>
